docs/source/conf.py
xreflection/__init__.py
xreflection/archs/__init__.py
xreflection/archs/discriminator_arch.py
xreflection/archs/dsit_arch.py
xreflection/archs/dsrnet_arch.py
xreflection/archs/rdnet_arch.py
xreflection/archs/swin.py
xreflection/archs/swin_det.py
xreflection/archs/vgg_arch.py
xreflection/archs/ytmt_arch.py
xreflection/archs/dsrnet/lrm.py
xreflection/archs/rdnet/classifier.py
xreflection/archs/rdnet/focalnet.py
xreflection/archs/rdnet/modules_sig.py
xreflection/archs/rdnet/revcol_function.py
xreflection/data/__init__.py
xreflection/data/dsit_dataset.py
xreflection/data/dsrnet_dataset.py
xreflection/data/image_folder.py
xreflection/data/prefetch_dataloader.py
xreflection/data/rdnet_dataset.py
xreflection/data/torchdata.py
xreflection/data/transforms.py
xreflection/losses/__init__.py
xreflection/losses/basic_loss.py
xreflection/losses/dsit_loss.py
xreflection/losses/gan_loss.py
xreflection/losses/loss_util.py
xreflection/losses/reflection_loss.py
xreflection/losses/vgg.py
xreflection/losses/vit_feature_extractor.py
xreflection/metrics/__init__.py
xreflection/metrics/fid.py
xreflection/metrics/metric_util.py
xreflection/metrics/niqe.py
xreflection/metrics/psnr_ssim.py
xreflection/metrics/test_metrics/test_psnr_ssim.py
xreflection/models/__init__.py
xreflection/models/base_model.py
xreflection/models/dsit_model.py
xreflection/models/dsrnet_model.py
xreflection/models/model_zoo.py
xreflection/models/rdnet_model.py
xreflection/tools/train.py
xreflection/utils/__init__.py
xreflection/utils/color_util.py
xreflection/utils/diffjpeg.py
xreflection/utils/download_util.py
xreflection/utils/ema_callback.py
xreflection/utils/file_client.py
xreflection/utils/flow_util.py
xreflection/utils/img_process_util.py
xreflection/utils/img_util.py
xreflection/utils/lmdb_util.py
xreflection/utils/lr_warmup_callback.py
xreflection/utils/matlab_functions.py
xreflection/utils/misc.py
xreflection/utils/plot_util.py
xreflection/utils/registry.py
xreflection-0.1.dist-info/METADATA
xreflection-0.1.dist-info/WHEEL
xreflection-0.1.dist-info/top_level.txt
xreflection-0.1.dist-info/RECORD
