Metadata-Version: 2.4
Name: xreflection
Version: 0.1
Summary: An Easy-to-use Toolbox for Single-image Reflection Removal
Author: Mingjia Li, Hainuo Wang, Jiarui Wang, Qiming Hu, Xiaojie Guo
Classifier: Programming Language :: Python :: 3
Classifier: Programming Language :: C++
Classifier: Operating System :: OS Independent
Requires-Python: >=3.6
Requires-Dist: pybind11
Requires-Dist: opencv-python
Requires-Dist: pillow
Requires-Dist: scipy
Requires-Dist: tqdm
Requires-Dist: torch
Requires-Dist: torchvision
Requires-Dist: pytorch-msssim
Requires-Dist: lightning
Requires-Dist: tensorboard
Requires-Dist: wandb>=0.12.10
Dynamic: requires-python
